pyaiodl/__init__.py
pyaiodl/__main__.py
pyaiodl/errors.py
pyaiodl/helper.py
pyaiodl/pyaiodl.py
pyaiodl/utils.py
pyaiodl-0.0.2.dist-info/METADATA
pyaiodl-0.0.2.dist-info/WHEEL
pyaiodl-0.0.2.dist-info/top_level.txt
pyaiodl-0.0.2.dist-info/RECORD
