Metadata-Version: 2.1
Name: pyaiodl
Version: 0.0.2
Summary: A Python Asynchronous Downloader - pyaiodl
Home-page: https://github.com/aryanvikash/pyaiodl
Author: Aryan Vikash
Author-email: followvikash8@gmail.com
License: UNKNOWN
Platform: UNKNOWN
Classifier: Programming Language :: Python :: 3
Classifier: Programming Language :: Python :: 3.7
Classifier: Programming Language :: Python :: 3.8
Classifier: License :: OSI Approved :: MIT License
Classifier: Topic :: Internet :: WWW/HTTP
Classifier: Topic :: Software Development :: Libraries :: Python Modules
Classifier: Operating System :: OS Independent
Requires-Python: >=3.7
Requires-Dist: aiohttp
Requires-Dist: fake-useragent
Requires-Dist: aiofiles
